{
  "id": "U105",
  "max_walking_time_to_origin": 3.4792194855788465,
  "max_walking_time_from_destination": 2.2575498843967283,
  "max_waiting_time": 11.79192945084366,
  "max_in_vehicle_time": 21.035391392382582,
  "max_cost": 29.89998394317724,
  "max_acceptable_delay": 8.695399165501712,
  "service_preference": "reliability",
  "weights": {
    "walking_time_to_origin": 0.4,
    "wait_time": 0.3,
    "in_vehicle_time": 0.2,
    "walking_time_from_destination": 0.1,
    "time_of_day": 0.0,
    "day_of_week": 0.0,
    "distance_to_pickup": 0.0
  },
  "historical_trips": 47,
  "historical_acceptance_rate": 0.5907890485736664,
  "historical_ratings": [
    3.5,
    3.6,
    3.4,
    4.7,
    4.3
  ]
}